{
  "schema": "anima/an11_v3_fixed_perm_re_measurement/1",
  "verifier": "V3 CPS (Gram Frob) with FIXED PRESERVE_PERM (raw#12 new revision)",
  "purpose": "raw#9 hexa-only ω-cycle. 1002d16a finding (V3 spec PAIRS↔PRESERVE_PERM partial mismatch on positions [3,4,5])이 V3 original metric (Gram Frob ratio)에 미치는 영향 분리. fixed PRESERVE_PERM = [6,7,8,10,11,9,0,1,2,3,4,5,12,13,14,15] (PAIRS와 일치)으로 재측정.",
  "spec_doc": "docs/v3_metric_redesign_v2_mirror_sma_20260425.md (sibling)",
  "ts": "2026-04-25",
  "preserve_perm_variants": {
    "original": [6,7,8,11,9,10,0,1,2,5,3,4,12,13,14,15],
    "fixed":    [6,7,8,10,11,9,0,1,2,3,4,5,12,13,14,15]
  },
  "results_BASE_p1": {
    "lasttoken": {
      "original": {
        "delta_preserve": 0.869793910098027,
        "delta_destruct": 0.811339214089569,
        "CPS": 0.932794774336981,
        "verdict": "FAIL"
      },
      "fixed": {
        "delta_preserve": 0.869417736325221,
        "delta_destruct": 0.811339214089569,
        "CPS": 0.933198369656993,
        "verdict": "FAIL"
      },
      "delta_fixed_minus_original": {
        "delta_preserve": -0.000376173772806,
        "delta_destruct": 0.0,
        "CPS": 0.000403595320012,
        "negligible": true
      }
    },
    "byte_weighted_mean": {
      "original": {
        "delta_preserve": 0.880600701673118,
        "delta_destruct": 0.826522149344284,
        "CPS": 0.938589019715649,
        "verdict": "FAIL"
      },
      "fixed": {
        "delta_preserve": 0.880229751666717,
        "delta_destruct": 0.826522149344284,
        "CPS": 0.938984563722440,
        "verdict": "FAIL"
      },
      "delta_fixed_minus_original": {
        "delta_preserve": -0.000370950006401,
        "delta_destruct": 0.0,
        "CPS": 0.000395544006791,
        "negligible": true
      }
    }
  },
  "key_finding": "V3 original Gram Frob metric은 PRESERVE_PERM mismatch에 거의 무영향 (Δ_CPS = +0.0004). V3 FALSIFIED는 spec mismatch가 아닌 metric 본질적 design flaw에 기인.",
  "why_negligible_impact_on_V3_original": [
    "V3 metric은 G_perm vs G의 전체 Frobenius distance — 16x16=256 matrix entries 중 PAIRS positions [3,4,5]만 mismatch 영향 (12 entries)",
    "12/256 = 4.7% entries 변경이 Frobenius L2 distance에 미치는 영향 미미",
    "반면 V3_v2 mirror-SMA는 PAIRS positions 6 entries만 직접 측정 → mismatch가 50% 영향 (3/6 pairs flipped)",
    "두 metric은 완전히 다른 axis를 측정"
  ],
  "implications": {
    "V3_original_metric": "spec mismatch가 fixed되어도 V3 FALSIFIED 결과 그대로. 진짜 문제는 metric design (preserve_perm이 destruct보다 더 큰 Gram disturbance를 본질적으로 일으킴) — spec fix로 해결 불가, 새 metric 필요.",
    "V3_v2_mirror_SMA": "spec mismatch가 큰 영향. fixed PRESERVE_PERM으로 재측정 시 DESTRUCT > PRESERVE 역전이 사라질 가능성 — 하지만 본 cycle scope 외, 별도 cycle 필요.",
    "spec_fix_decision": "Option B (PRESERVE_PERM 수정)는 V3 original에 거의 무영향 — V3 FALSIFIED resolve 불가. Option C (새 verifier 5-tuple expansion)가 여전히 권장. 또는 Option A (PAIRS 수정)는 V2 SMA에 영향, V3 V_v2에 영향 — 하지만 V3 original엔 무영향."
  },
  "saturation_finding": "V3 metric redesign cycle 종료점: spec mismatch는 일부 metric (V3_v2 mirror-SMA)에 영향 큼 + 일부 metric (V3 original Gram Frob)에 무영향. 즉 V3 진짜 fix는 (a) PRESERVE_PERM/PAIRS 정합 + (b) 본질적으로 다른 metric (paired-rank, semantic-substitution, etc.) 둘 다 필요. spec fix만으로는 4-tuple PASS unblock 불가.",
  "next_cycle_priority_post_finding": [
    "P1: 새 V3 verifier (paired-rank stability or semantic-substitution) spec design — Option C 5-tuple expansion path",
    "P2: V2 multi-axis PAPO TRAINED forward measurement (k=3 PASS in TRAINED?) — GPU 필요",
    "P3: V1 prompt 16->32 forward measurement — GPU 필요",
    "P4: Mk.X T10-13 G1-G4 gate fire criteria pre-register — $0 spec"
  ],
  "raw_compliance": {
    "raw_9_hexa_only_deterministic": "satisfied — CPU only, $0",
    "raw_10_no_overclaim": "satisfied — fixed perm Δ=+0.0004 negligible 명시, V3 FALSIFIED resolve 불가 정직 보고",
    "raw_12_cherry_pick_proof": "satisfied — fixed PRESERVE_PERM은 raw#12 new revision으로 등록 (original 보존), result file에 preserve_perm_variant='fixed' 명시",
    "raw_15_ssot": "this file = SSOT for fixed-perm re-measurement",
    "raw_37_38_omega_saturation_cycle": "design (V3 spec fix decision rationale) → impl (tool --fixed-perm flag + measurement + this finding) → fixpoint marker"
  }
}
