{
  "paradigm": ".gitignore comprehensive audit (raw#9 strict + 6-category breakdown)",
  "root_gitignore": {
    "path": ".gitignore",
    "present": true,
    "line_count": 150,
    "pattern_count": 82,
    "category_breakdown": {
      "python_or_venv": 7,
      "other": 29,
      "secrets_local": 12,
      "model_files": 7,
      "corpus_data": 15,
      "state_cache": 8,
      "build_ide": 4
    },
    "patterns_sample": [
      "**/*.py",
      "__pycache__/",
      "*.pyc",
      "*.egg-info/",
      ".venv/"
    ],
    "has_raw9_py_rule": true
  },
  "sub_gitignores": [
    {
      "path": "ready/.gitignore",
      "present": true,
      "line_count": 67,
      "pattern_count": 39,
      "category_breakdown": {
        "python_or_venv": 4,
        "other": 16,
        "secrets_local": 11,
        "model_files": 4,
        "corpus_data": 4
      },
      "patterns_sample": [
        "__pycache__/",
        "*.pyc",
        "*.egg-info/",
        ".venv/",
        "venv/"
      ],
      "has_raw9_py_rule": false
    },
    {
      "path": "ready/.pytest_cache/.gitignore",
      "present": true,
      "line_count": 2,
      "pattern_count": 1,
      "category_breakdown": {
        "other": 1
      },
      "patterns_sample": [
        "*"
      ],
      "has_raw9_py_rule": false
    },
    {
      "path": "ready/anima-agent/.pytest_cache/.gitignore",
      "present": true,
      "line_count": 2,
      "pattern_count": 1,
      "category_breakdown": {
        "other": 1
      },
      "patterns_sample": [
        "*"
      ],
      "has_raw9_py_rule": false
    },
    {
      "path": "ready/anima/.gitignore",
      "present": true,
      "line_count": 38,
      "pattern_count": 29,
      "category_breakdown": {
        "python_or_venv": 4,
        "other": 11,
        "secrets_local": 2,
        "model_files": 4,
        "corpus_data": 8
      },
      "patterns_sample": [
        "__pycache__/",
        "*.pyc",
        "*.egg-info/",
        "!package.json",
        ".env"
      ],
      "has_raw9_py_rule": false
    },
    {
      "path": "ready/anima/.pytest_cache/.gitignore",
      "present": true,
      "line_count": 2,
      "pattern_count": 1,
      "category_breakdown": {
        "other": 1
      },
      "patterns_sample": [
        "*"
      ],
      "has_raw9_py_rule": false
    },
    {
      "path": "ready/anima/models/.cache/huggingface/.gitignore",
      "present": true,
      "line_count": 1,
      "pattern_count": 1,
      "category_breakdown": {
        "other": 1
      },
      "patterns_sample": [
        "*"
      ],
      "has_raw9_py_rule": false
    },
    {
      "path": "ready/checkpoints/.gitignore",
      "present": true,
      "line_count": 1,
      "pattern_count": 1,
      "category_breakdown": {
        "other": 1
      },
      "patterns_sample": [
        "*.txt"
      ],
      "has_raw9_py_rule": false
    },
    {
      "path": ".pytest_cache/.gitignore",
      "present": true,
      "line_count": 2,
      "pattern_count": 1,
      "category_breakdown": {
        "other": 1
      },
      "patterns_sample": [
        "*"
      ],
      "has_raw9_py_rule": false
    },
    {
      "path": "references/tribev2/.gitignore",
      "present": true,
      "line_count": 35,
      "pattern_count": 23,
      "category_breakdown": {
        "python_or_venv": 6,
        "other": 9,
        "build_ide": 4,
        "state_cache": 2,
        "model_files": 1,
        "secrets_local": 1
      },
      "patterns_sample": [
        "__pycache__/",
        "*.pyc",
        "*.pyo",
        "*.egg-info/",
        "dist/"
      ],
      "has_raw9_py_rule": false
    },
    {
      "path": "training/native/.gitignore",
      "present": true,
      "line_count": 3,
      "pattern_count": 3,
      "category_breakdown": {
        "other": 3
      },
      "patterns_sample": [
        "libtrain_step*.so",
        "*.o",
        "train_step_test"
      ],
      "has_raw9_py_rule": false
    },
    {
      "path": "training/corpus_auto/raw/kowiki/.cache/huggingface/.gitignore",
      "present": true,
      "line_count": 1,
      "pattern_count": 1,
      "category_breakdown": {
        "other": 1
      },
      "patterns_sample": [
        "*"
      ],
      "has_raw9_py_rule": false
    },
    {
      "path": "anima/.gitignore",
      "present": true,
      "line_count": 38,
      "pattern_count": 29,
      "category_breakdown": {
        "python_or_venv": 4,
        "other": 11,
        "secrets_local": 2,
        "model_files": 4,
        "corpus_data": 8
      },
      "patterns_sample": [
        "__pycache__/",
        "*.pyc",
        "*.egg-info/",
        "!package.json",
        ".env"
      ],
      "has_raw9_py_rule": false
    },
    {
      "path": "checkpoints/.gitignore",
      "present": true,
      "line_count": 1,
      "pattern_count": 1,
      "category_breakdown": {
        "other": 1
      },
      "patterns_sample": [
        "*.txt"
      ],
      "has_raw9_py_rule": false
    }
  ],
  "sub_count": 13,
  "critical_patterns": {
    "python_blanket": true,
    "category_python": true,
    "category_secrets": true,
    "category_models": true,
    "category_corpus": true,
    "category_state": true
  },
  "raw9_strict_policy": {
    "root_has_py_rule": true,
    "sub_with_py_rule": 0,
    "enforcement_observed_in_session": "cycles 1-25 batch — _all_kick_extract_run.py blocked from commit (gitignore active)",
    "cross_link": "cycle 22 tool/ inventory raw#9 header 57.6% (helper-side compliance, separate from .py blanket ignore)"
  },
  "non_mutation_guarantee": "helper does NOT modify .gitignore; read-only audit",
  "cross_link_cycles": [
    "cycle 22 tool/ raw#9 header 57.6%",
    "cycles 1-25 batch all helpers .py-emit blocked"
  ],
  "pattern": "5-layer governance audit chain extension (cycle 21-25 + this)"
}