{
  "schema": "anima/h100_auto_kill_dryrun/1",
  "generated_at": "2026-04-22T09:15:36Z",
  "tool": "tool/h100_auto_kill.hexa",
  "config_source": "config/h100_auto_kill_config.json",
  "idle_threshold_minutes": 30,
  "threshold_confirmed": true,
  "kill_triggers_identified": [
    {
      "trigger": "idle_minutes >= threshold_minutes",
      "implemented": true,
      "code_ref": "tool/h100_auto_kill.hexa:_evaluate_pod L168",
      "verdict_emitted": "STOP",
      "stop_cmd_template": "runpodctl stop pod {pod_id}"
    },
    {
      "trigger": "malformed_pod_entry (missing pod_id|provider|last_activity_source)",
      "implemented": true,
      "code_ref": "tool/h100_auto_kill.hexa:_evaluate_pod L141-L153",
      "verdict_emitted": "SKIP"
    },
    {
      "trigger": "no_probe_result (idle_minutes < 0 in dry-run, no mock)",
      "implemented": true,
      "code_ref": "tool/h100_auto_kill.hexa:_evaluate_pod L163-L167",
      "verdict_emitted": "UNKNOWN"
    },
    {
      "trigger": "NaN_detect",
      "implemented": false,
      "note": "Out-of-scope for this guard; belongs to training-loop loss-monitor (separate tool)."
    },
    {
      "trigger": "budget_breach",
      "implemented": false,
      "note": "Cost-budget guard is separate (h100_budget_*.hexa); auto_kill operates on idle-time only."
    },
    {
      "trigger": "phi_divergence",
      "implemented": false,
      "note": "Φ-divergence detector is part of phi monitor; auto_kill does not consume Φ signals."
    }
  ],
  "kill_apply_gating": {
    "default_mode": "dry-run",
    "apply_flag_required": true,
    "apply_flag": "--apply",
    "runpodctl_required_on_path": true,
    "fallback_when_runpodctl_absent": "echo STOP <pod_id> stub (apply_note=runpodctl_not_on_path_stub)"
  },
  "simulation": {
    "mode": "cpu_only_logic_trace",
    "method": "applied _evaluate_pod logic by hand against 4 synthetic pods; runpodctl NOT invoked; no SSH; no state mutation of last_run.json",
    "conversion": "idle_minutes = floor(last_log_age_seconds / 60)"
  },
  "simulated_pods": [
    {
      "pod_id": "mock-A-fresh",
      "last_log_age_s": 120,
      "idle_minutes": 2,
      "threshold_minutes": 30,
      "would_kill": false,
      "reason": "KEEP — idle (2min) < threshold (30min)"
    },
    {
      "pod_id": "mock-B-near-edge",
      "last_log_age_s": 1700,
      "idle_minutes": 28,
      "threshold_minutes": 30,
      "would_kill": false,
      "reason": "KEEP — idle (28min) < threshold (30min); within 2min of edge"
    },
    {
      "pod_id": "mock-C-just-over",
      "last_log_age_s": 1900,
      "idle_minutes": 31,
      "threshold_minutes": 30,
      "would_kill": true,
      "reason": "STOP — idle (31min) >= threshold (30min); stop_cmd='runpodctl stop pod mock-C-just-over' (NOT EXECUTED — dry-run)"
    },
    {
      "pod_id": "mock-D-stale-2h",
      "last_log_age_s": 7200,
      "idle_minutes": 120,
      "threshold_minutes": 30,
      "would_kill": true,
      "reason": "STOP — idle (120min) >= threshold (30min); stop_cmd='runpodctl stop pod mock-D-stale-2h' (NOT EXECUTED — dry-run)"
    }
  ],
  "simulated_summary": {
    "stops": 2,
    "keeps": 2,
    "skips": 0,
    "unknowns": 0
  },
  "self_test_reference": {
    "exists": true,
    "scenarios": 3,
    "code_ref": "tool/h100_auto_kill.hexa:self_test L318-L354",
    "matches_expected_logic": true
  },
  "side_effects": {
    "runpodctl_invoked": false,
    "ssh_invoked": false,
    "state_files_modified": [],
    "last_run_proof_overwritten": false
  },
  "verdict": "PASS",
  "notes": "Threshold confirmed at 30min in config/h100_auto_kill_config.json and hard-coded default in _evaluate_pod (L155). 4-pod simulation matches expected STOP/KEEP boundary at 30min. NaN/budget/Φ triggers are intentionally OUT of scope for this guard — handled by separate tools. Dry-run safe: no runpodctl/ssh calls, no shared state writes."
}
