{
  "schema": "anima/reproducible_emit_audit/1",
  "generated_at": "2026-04-22T11:53:31Z",
  "generated_at_epoch": 1776858811,
  "generator": "tool/reproducible_emit_check.hexa (manual audit)",
  "upstream_ref": "docs/upstream_notes/hexa_lang_20260422.md PR #23",
  "primitives_honoring_env": [
    "now()",
    "timestamp()",
    "time_ms()",
    "utc_iso_now()",
    "utc_compact_now()"
  ],
  "env_vars": {
    "SOURCE_DATE_EPOCH": "pin all timestamp primitives to <unix_seconds>",
    "HEXA_REPRODUCIBLE": "1 → pin to epoch 0 (1970-01-01T00:00:00Z)"
  },
  "tools": [
    {
      "path": "tool/h100_launch_manifest_spec.hexa",
      "status": "NATIVE_PRIMITIVE",
      "notes": "Refactored: _ts_iso → utc_iso_now(); _ts_epoch → now(). SDE re-emit verified byte-stable via tool/reproducible_emit_check.hexa.",
      "emits": "state/h100_launch_manifest.json"
    },
    {
      "path": "tool/h100_post_launch_ingest.hexa",
      "status": "NATIVE_PRIMITIVE",
      "notes": "Refactored: _ts_iso → utc_iso_now(); _ts_epoch → now().",
      "emits": "state/h100_post_launch_ingest.json"
    },
    {
      "path": "tool/h100_auto_kill.hexa",
      "status": "NATIVE_PRIMITIVE",
      "notes": "Refactored: _ts_iso → utc_iso_now(); _ts_epoch → now().",
      "emits": "state/h100_auto_kill_*.json"
    },
    {
      "path": "tool/l3_pre_launch_validate.hexa",
      "status": "NATIVE_PRIMITIVE",
      "notes": "Refactored: _ts_iso wrapping `exec(\"date -u +%FT%TZ\")` → utc_iso_now().",
      "emits": "state/l3_pre_launch_validate.json"
    },
    {
      "path": "tool/slack_notify_launch_verdict.hexa",
      "status": "NOT_APPLICABLE",
      "notes": "Reads existing generated_at from input JSON; does not emit timestamps."
    },
    {
      "path": "tool/statusline_h100_burn.hexa",
      "status": "NOT_APPLICABLE",
      "notes": "Read-only statusline, no state emission."
    }
  ],
  "tools_status_count": {
    "NATIVE_PRIMITIVE": 4,
    "NEEDS_REFACTOR": 0,
    "NOT_APPLICABLE": 2
  },
  "ci_helper": {
    "path": "tool/reproducible_emit_check.hexa",
    "default_target": "tool/h100_launch_manifest_spec.hexa",
    "default_emit": "state/h100_launch_manifest.json",
    "smoke_verdict": "PASS",
    "verified_at": "2026-04-22T11:53:00Z",
    "method": "snapshot baseline → run with SDE → snapshot → restore baseline → re-run with same SDE → snapshot → sha256 equality assertion → restore baseline (no side effects)"
  },
  "out_of_scope_emitters_with_date_exec": {
    "note": "These tools also exec `date -u …` for emission timestamps but were not refactored per task scope. Future work: same _ts_iso → utc_iso_now() swap.",
    "count": "see grep -l 'date -u' tool/*.hexa (~115 hits at audit time)",
    "next_batch_targets": [
      "tool/cert_dag_generator.hexa",
      "tool/sbom_generate.hexa",
      "tool/code_quality_audit_summary.hexa",
      "tool/lint_rule_pack.hexa",
      "tool/auto_changelog.hexa"
    ]
  },
  "workflow_doc": "docs/reproducible_emit_workflow.md",
  "constraint_compliance": {
    "no_roadmap_edits": true,
    "no_emitter_behavior_change": "only manual `date -u` exec → primitive swap; default behavior identical when env unset",
    "no_commit": true,
    "no_py_files": true,
    "default_unset_unchanged": "verified — generated_at = 2026-04-22T11:51:44Z (live wall clock) when SDE/HEXA_REPRODUCIBLE both absent"
  }
}
