{
  "schema": "anima.serve_alm_persona_boot_dryrun.v1",
  "slug": "serve-alm-persona-boot-dryrun",
  "tool": "tool/serve_alm_persona.hexa",
  "sap_version": "serve_alm_persona/1.0.0",
  "roadmap_entry": "77",
  "checkpoint": "CP1 — dest1 persona LIVE",
  "created": "2026-04-22T09:49:31Z",
  "mode": "dry",
  "port": 8000,
  "persona_id": "dest1",
  "persona_layer_idx": 20,
  "phi_layer_idx": 24,
  "phi_dims": 16,
  "config_present": true,
  "lora_config_present": true,
  "swap_in_artifacts": [
    {"key": "base_model_path",  "status": "MISSING"},
    {"key": "persona_lora_path", "status": "MISSING"},
    {"key": "fastapi_body_path", "status": "STAGED_FOR_POD"},
    {"key": "h_last_ffi_path",  "status": "STAGED"}
  ],
  "endpoints": [
    {"path": "/health",   "method": "GET"},
    {"path": "/personas", "method": "GET"},
    {"path": "/persona",  "method": "POST", "gates": ["cert_gate", "an11_a"]}
  ],
  "backend_status": "BACKEND_PENDING — base_model + persona_lora not yet on local disk; H100 cascade #9 is the producer",
  "raw_compliance": ["raw#9", "raw#10", "raw#11", "raw#12", "raw#15"],
  "verdict": "BOOT_DRYRUN_OK"
}
